mangala_kutuphanesi/__init__.py
mangala_kutuphanesi/cli.py
mangala_kutuphanesi/oyun.py
mangala-1.0.0.dist-info/METADATA
mangala-1.0.0.dist-info/WHEEL
mangala-1.0.0.dist-info/entry_points.txt
mangala-1.0.0.dist-info/top_level.txt
mangala-1.0.0.dist-info/RECORD
