Metadata-Version: 2.4
Name: mangala
Version: 1.0.0
Summary: Türk zeka ve strateji oyunu Mangala için bir kütüphane ve komut satırı oyunu.
Author: saveralf
Classifier: Programming Language :: Python :: 3
Classifier: License :: OSI Approved :: MIT License
Classifier: Operating System :: OS Independent
Classifier: Topic :: Games/Entertainment :: Board Games
Requires-Python: >=3.7
